[
  {
    "pdf_file": "43.pdf",
    "sr_no": null,
    "crime_head": "No.",
    "current_month_reg": "",
    "current_month_det": "Mo",
    "previous_month_reg": "nth",
    "previous_month_det": "Mo",
    "current_year_reg": "nth",
    "current_year_det": "Y",
    "current_year_det_pct": "ear",
    "previous_year_reg": "of",
    "previous_year_det": "Y",
    "previous_year_det_pct": "ear",
    "diff_reg_sign": "of",
    "diff_reg_value": "-",
    "current_month_start": "01.05.2021",
    "current_month_end": "01.04.2021",
    "current_month": "2021-05",
    "previous_month_start": "01.01.2021",
    "previous_month_end": "01.01.2020",
    "current_year_start": "31.05.2021",
    "current_year_end": "30.04.2021",
    "previous_year_start": "31.05.2020",
    "previous_year_end": ""
  },
  {
    "pdf_file": "43.pdf",
    "sr_no": 1,
    "crime_head": "Murder",
    "current_month_reg": "22",
    "current_month_det": "20",
    "previous_month_reg": "7",
    "previous_month_det": "6",
    "current_year_reg": "73",
    "current_year_det": "69",
    "current_year_det_pct": "95",
    "previous_year_reg": "58",
    "previous_year_det": "53",
    "previous_year_det_pct": "91",
    "diff_reg_sign": "+",
    "diff_reg_value": "15",
    "current_month_start": "01.05.2021",
    "current_month_end": "01.04.2021",
    "current_month": "2021-05",
    "previous_month_start": "01.01.2021",
    "previous_month_end": "01.01.2020",
    "current_year_start": "31.05.2021",
    "current_year_end": "30.04.2021",
    "previous_year_start": "31.05.2020",
    "previous_year_end": ""
  },
  {
    "pdf_file": "43.pdf",
    "sr_no": 2,
    "crime_head": "Att.to.C.Murder",
    "current_month_reg": "42",
    "current_month_det": "38",
    "previous_month_reg": "27",
    "previous_month_det": "24",
    "current_year_reg": "169",
    "current_year_det": "161",
    "current_year_det_pct": "95",
    "previous_year_reg": "122",
    "previous_year_det": "116",
    "previous_year_det_pct": "95",
    "diff_reg_sign": "+",
    "diff_reg_value": "47",
    "current_month_start": "01.05.2021",
    "current_month_end": "01.04.2021",
    "current_month": "2021-05",
    "previous_month_start": "01.01.2021",
    "previous_month_end": "01.01.2020",
    "current_year_start": "31.05.2021",
    "current_year_end": "30.04.2021",
    "previous_year_start": "31.05.2020",
    "previous_year_end": ""
  },
  {
    "pdf_file": "43.pdf",
    "sr_no": 3,
    "crime_head": "Dacoity",
    "current_month_reg": "0",
    "current_month_det": "0",
    "previous_month_reg": "1",
    "previous_month_det": "1",
    "current_year_reg": "8",
    "current_year_det": "6",
    "current_year_det_pct": "75",
    "previous_year_reg": "5",
    "previous_year_det": "4",
    "previous_year_det_pct": "80",
    "diff_reg_sign": "+",
    "diff_reg_value": "3",
    "current_month_start": "01.05.2021",
    "current_month_end": "01.04.2021",
    "current_month": "2021-05",
    "previous_month_start": "01.01.2021",
    "previous_month_end": "01.01.2020",
    "current_year_start": "31.05.2021",
    "current_year_end": "30.04.2021",
    "previous_year_start": "31.05.2020",
    "previous_year_end": ""
  },
  {
    "pdf_file": "43.pdf",
    "sr_no": 4,
    "crime_head": "Robbery (Excluding Chain Snatc hing)",
    "current_month_reg": "55",
    "current_month_det": "48",
    "previous_month_reg": "40",
    "previous_month_det": "28",
    "current_year_reg": "300",
    "current_year_det": "265",
    "current_year_det_pct": "88",
    "previous_year_reg": "247",
    "previous_year_det": "206",
    "previous_year_det_pct": "83",
    "diff_reg_sign": "+",
    "diff_reg_value": "53",
    "current_month_start": "01.05.2021",
    "current_month_end": "01.04.2021",
    "current_month": "2021-05",
    "previous_month_start": "01.01.2021",
    "previous_month_end": "01.01.2020",
    "current_year_start": "31.05.2021",
    "current_year_end": "30.04.2021",
    "previous_year_start": "31.05.2020",
    "previous_year_end": ""
  },
  {
    "pdf_file": "43.pdf",
    "sr_no": 5,
    "crime_head": "Robbery -Chain Snatching",
    "current_month_reg": "6",
    "current_month_det": "4",
    "previous_month_reg": "4",
    "previous_month_det": "2",
    "current_year_reg": "48",
    "current_year_det": "30",
    "current_year_det_pct": "63",
    "previous_year_reg": "44",
    "previous_year_det": "34",
    "previous_year_det_pct": "77",
    "diff_reg_sign": "+",
    "diff_reg_value": "4",
    "current_month_start": "01.05.2021",
    "current_month_end": "01.04.2021",
    "current_month": "2021-05",
    "previous_month_start": "01.01.2021",
    "previous_month_end": "01.01.2020",
    "current_year_start": "31.05.2021",
    "current_year_end": "30.04.2021",
    "previous_year_start": "31.05.2020",
    "previous_year_end": ""
  },
  {
    "pdf_file": "43.pdf",
    "sr_no": 6,
    "crime_head": "Extortion",
    "current_month_reg": "21",
    "current_month_det": "15",
    "previous_month_reg": "12",
    "previous_month_det": "5",
    "current_year_reg": "120",
    "current_year_det": "91",
    "current_year_det_pct": "76",
    "previous_year_reg": "84",
    "previous_year_det": "74",
    "previous_year_det_pct": "88",
    "diff_reg_sign": "+",
    "diff_reg_value": "36",
    "current_month_start": "01.05.2021",
    "current_month_end": "01.04.2021",
    "current_month": "2021-05",
    "previous_month_start": "01.01.2021",
    "previous_month_end": "01.01.2020",
    "current_year_start": "31.05.2021",
    "current_year_end": "30.04.2021",
    "previous_year_start": "31.05.2020",
    "previous_year_end": ""
  },
  {
    "pdf_file": "43.pdf",
    "sr_no": 7,
    "crime_head": "H.B.T.Day / Night",
    "current_month_reg": "104",
    "current_month_det": "37",
    "previous_month_reg": "95",
    "previous_month_det": "31",
    "current_year_reg": "641",
    "current_year_det": "294",
    "current_year_det_pct": "46",
    "previous_year_reg": "559",
    "previous_year_det": "231",
    "previous_year_det_pct": "41",
    "diff_reg_sign": "+",
    "diff_reg_value": "82",
    "current_month_start": "01.05.2021",
    "current_month_end": "01.04.2021",
    "current_month": "2021-05",
    "previous_month_start": "01.01.2021",
    "previous_month_end": "01.01.2020",
    "current_year_start": "31.05.2021",
    "current_year_end": "30.04.2021",
    "previous_year_start": "31.05.2020",
    "previous_year_end": ""
  },
  {
    "pdf_file": "43.pdf",
    "sr_no": 8,
    "crime_head": "Thefts",
    "current_month_reg": "303",
    "current_month_det": "106",
    "previous_month_reg": "258",
    "previous_month_det": "66",
    "current_year_reg": "1,690",
    "current_year_det": "632",
    "current_year_det_pct": "37",
    "previous_year_reg": "1,383",
    "previous_year_det": "416",
    "previous_year_det_pct": "30",
    "diff_reg_sign": "+",
    "diff_reg_value": "307",
    "current_month_start": "01.05.2021",
    "current_month_end": "01.04.2021",
    "current_month": "2021-05",
    "previous_month_start": "01.01.2021",
    "previous_month_end": "01.01.2020",
    "current_year_start": "31.05.2021",
    "current_year_end": "30.04.2021",
    "previous_year_start": "31.05.2020",
    "previous_year_end": ""
  },
  {
    "pdf_file": "43.pdf",
    "sr_no": 9,
    "crime_head": "M.V.Thefts.",
    "current_month_reg": "247",
    "current_month_det": "49",
    "previous_month_reg": "198",
    "previous_month_det": "39",
    "current_year_reg": "1,345",
    "current_year_det": "509",
    "current_year_det_pct": "38",
    "previous_year_reg": "883",
    "previous_year_det": "220",
    "previous_year_det_pct": "25",
    "diff_reg_sign": "+",
    "diff_reg_value": "462",
    "current_month_start": "01.05.2021",
    "current_month_end": "01.04.2021",
    "current_month": "2021-05",
    "previous_month_start": "01.01.2021",
    "previous_month_end": "01.01.2020",
    "current_year_start": "31.05.2021",
    "current_year_end": "30.04.2021",
    "previous_year_start": "31.05.2020",
    "previous_year_end": ""
  },
  {
    "pdf_file": "43.pdf",
    "sr_no": 10,
    "crime_head": "Hurt",
    "current_month_reg": "419",
    "current_month_det": "322",
    "previous_month_reg": "321",
    "previous_month_det": "246",
    "current_year_reg": "1,874",
    "current_year_det": "1,627",
    "current_year_det_pct": "87",
    "previous_year_reg": "1,466",
    "previous_year_det": "1,122",
    "previous_year_det_pct": "77",
    "diff_reg_sign": "+",
    "diff_reg_value": "408",
    "current_month_start": "01.05.2021",
    "current_month_end": "01.04.2021",
    "current_month": "2021-05",
    "previous_month_start": "01.01.2021",
    "previous_month_end": "01.01.2020",
    "current_year_start": "31.05.2021",
    "current_year_end": "30.04.2021",
    "previous_year_start": "31.05.2020",
    "previous_year_end": ""
  },
  {
    "pdf_file": "43.pdf",
    "sr_no": 11,
    "crime_head": "Riots.",
    "current_month_reg": "33",
    "current_month_det": "28",
    "previous_month_reg": "27",
    "previous_month_det": "19",
    "current_year_reg": "138",
    "current_year_det": "114",
    "current_year_det_pct": "83",
    "previous_year_reg": "132",
    "previous_year_det": "94",
    "previous_year_det_pct": "71",
    "diff_reg_sign": "+",
    "diff_reg_value": "6",
    "current_month_start": "01.05.2021",
    "current_month_end": "01.04.2021",
    "current_month": "2021-05",
    "previous_month_start": "01.01.2021",
    "previous_month_end": "01.01.2020",
    "current_year_start": "31.05.2021",
    "current_year_end": "30.04.2021",
    "previous_year_start": "31.05.2020",
    "previous_year_end": ""
  },
  {
    "pdf_file": "43.pdf",
    "sr_no": 12,
    "crime_head": "Rape",
    "current_month_reg": "71",
    "current_month_det": "43",
    "previous_month_reg": "66",
    "previous_month_det": "41",
    "current_year_reg": "395",
    "current_year_det": "295",
    "current_year_det_pct": "75",
    "previous_year_reg": "276",
    "previous_year_det": "220",
    "previous_year_det_pct": "80",
    "diff_reg_sign": "+",
    "diff_reg_value": "119",
    "current_month_start": "01.05.2021",
    "current_month_end": "01.04.2021",
    "current_month": "2021-05",
    "previous_month_start": "01.01.2021",
    "previous_month_end": "01.01.2020",
    "current_year_start": "31.05.2021",
    "current_year_end": "30.04.2021",
    "previous_year_start": "31.05.2020",
    "previous_year_end": ""
  },
  {
    "pdf_file": "43.pdf",
    "sr_no": 13,
    "crime_head": "Molestaion",
    "current_month_reg": "136",
    "current_month_det": "86",
    "previous_month_reg": "139",
    "previous_month_det": "94",
    "current_year_reg": "792",
    "current_year_det": "599",
    "current_year_det_pct": "76",
    "previous_year_reg": "797",
    "previous_year_det": "594",
    "previous_year_det_pct": "75",
    "diff_reg_sign": "-",
    "diff_reg_value": "5",
    "current_month_start": "01.05.2021",
    "current_month_end": "01.04.2021",
    "current_month": "2021-05",
    "previous_month_start": "01.01.2021",
    "previous_month_end": "01.01.2020",
    "current_year_start": "31.05.2021",
    "current_year_end": "30.04.2021",
    "previous_year_start": "31.05.2020",
    "previous_year_end": ""
  },
  {
    "pdf_file": "43.pdf",
    "sr_no": 14,
    "crime_head": "Other I.P.C.",
    "current_month_reg": "13,613",
    "current_month_det": "13,063",
    "previous_month_reg": "7,844",
    "previous_month_det": "7,326",
    "current_year_reg": "26,692",
    "current_year_det": "24,140",
    "current_year_det_pct": "90",
    "previous_year_reg": "12,994",
    "previous_year_det": "10,671",
    "previous_year_det_pct": "82",
    "diff_reg_sign": "+",
    "diff_reg_value": "13,698",
    "current_month_start": "01.05.2021",
    "current_month_end": "01.04.2021",
    "current_month": "2021-05",
    "previous_month_start": "01.01.2021",
    "previous_month_end": "01.01.2020",
    "current_year_start": "31.05.2021",
    "current_year_end": "30.04.2021",
    "previous_year_start": "31.05.2020",
    "previous_year_end": ""
  },
  {
    "pdf_file": "43.pdf",
    "sr_no": null,
    "crime_head": "Total",
    "current_month_reg": "15,072",
    "current_month_det": "13,859",
    "previous_month_reg": "9,039",
    "previous_month_det": "7,928",
    "current_year_reg": "34,285",
    "current_year_det": "28,832",
    "current_year_det_pct": "84",
    "previous_year_reg": "19,050",
    "previous_year_det": "14,055",
    "previous_year_det_pct": "74",
    "diff_reg_sign": "+",
    "diff_reg_value": "15,235",
    "current_month_start": "01.05.2021",
    "current_month_end": "01.04.2021",
    "current_month": "2021-05",
    "previous_month_start": "01.01.2021",
    "previous_month_end": "01.01.2020",
    "current_year_start": "31.05.2021",
    "current_year_end": "30.04.2021",
    "previous_year_start": "31.05.2020",
    "previous_year_end": ""
  }
]