[
  {
    "pdf_file": "78.pdf",
    "sr_no": 1,
    "crime_head": "Murder",
    "current_month_reg": "8",
    "current_month_det": "8",
    "previous_month_reg": "9",
    "previous_month_det": "8",
    "current_year_reg": "17",
    "current_year_det": "17",
    "current_year_det_pct": "",
    "previous_year_reg": "89",
    "previous_year_det": "",
    "previous_year_det_pct": "20",
    "diff_reg_sign": "19",
    "diff_reg_value": "",
    "current_month_start": "02.01.2024",
    "current_month_end": "01.01.2024",
    "current_month": "2024-01",
    "previous_month_start": "01.02.2023",
    "previous_month_end": "29.02.2024",
    "current_year_start": "31.01.2024",
    "current_year_end": "02.29.2023",
    "previous_year_start": "",
    "previous_year_end": ""
  },
  {
    "pdf_file": "78.pdf",
    "sr_no": 2,
    "crime_head": "Att.to.C.Murder",
    "current_month_reg": "26",
    "current_month_det": "24",
    "previous_month_reg": "27",
    "previous_month_det": "27",
    "current_year_reg": "54",
    "current_year_det": "52",
    "current_year_det_pct": "",
    "previous_year_reg": "100",
    "previous_year_det": "",
    "previous_year_det_pct": "42",
    "diff_reg_sign": "39",
    "diff_reg_value": "",
    "current_month_start": "02.01.2024",
    "current_month_end": "01.01.2024",
    "current_month": "2024-01",
    "previous_month_start": "01.02.2023",
    "previous_month_end": "29.02.2024",
    "current_year_start": "31.01.2024",
    "current_year_end": "02.29.2023",
    "previous_year_start": "",
    "previous_year_end": ""
  },
  {
    "pdf_file": "78.pdf",
    "sr_no": 3,
    "crime_head": "Dacoity",
    "current_month_reg": "2",
    "current_month_det": "2",
    "previous_month_reg": "2",
    "previous_month_det": "2",
    "current_year_reg": "4",
    "current_year_det": "4",
    "current_year_det_pct": "",
    "previous_year_reg": "100",
    "previous_year_det": "",
    "previous_year_det_pct": "5",
    "diff_reg_sign": "4",
    "diff_reg_value": "",
    "current_month_start": "02.01.2024",
    "current_month_end": "01.01.2024",
    "current_month": "2024-01",
    "previous_month_start": "01.02.2023",
    "previous_month_end": "29.02.2024",
    "current_year_start": "31.01.2024",
    "current_year_end": "02.29.2023",
    "previous_year_start": "",
    "previous_year_end": ""
  },
  {
    "pdf_file": "78.pdf",
    "sr_no": 4,
    "crime_head": "Prep.for Dacoity",
    "current_month_reg": "1",
    "current_month_det": "1",
    "previous_month_reg": "2",
    "previous_month_det": "2",
    "current_year_reg": "3",
    "current_year_det": "3",
    "current_year_det_pct": "",
    "previous_year_reg": "100",
    "previous_year_det": "",
    "previous_year_det_pct": "4",
    "diff_reg_sign": "4",
    "diff_reg_value": "",
    "current_month_start": "02.01.2024",
    "current_month_end": "01.01.2024",
    "current_month": "2024-01",
    "previous_month_start": "01.02.2023",
    "previous_month_end": "29.02.2024",
    "current_year_start": "31.01.2024",
    "current_year_end": "02.29.2023",
    "previous_year_start": "",
    "previous_year_end": ""
  },
  {
    "pdf_file": "78.pdf",
    "sr_no": 5,
    "crime_head": "Robbery",
    "current_month_reg": "52",
    "current_month_det": "46",
    "previous_month_reg": "50",
    "previous_month_det": "39",
    "current_year_reg": "102",
    "current_year_det": "94",
    "current_year_det_pct": "",
    "previous_year_reg": "78",
    "previous_year_det": "",
    "previous_year_det_pct": "108",
    "diff_reg_sign": "98",
    "diff_reg_value": "",
    "current_month_start": "02.01.2024",
    "current_month_end": "01.01.2024",
    "current_month": "2024-01",
    "previous_month_start": "01.02.2023",
    "previous_month_end": "29.02.2024",
    "current_year_start": "31.01.2024",
    "current_year_end": "02.29.2023",
    "previous_year_start": "",
    "previous_year_end": ""
  },
  {
    "pdf_file": "78.pdf",
    "sr_no": 6,
    "crime_head": "Robbery-Chain",
    "current_month_reg": "14",
    "current_month_det": "8",
    "previous_month_reg": "10",
    "previous_month_det": "6",
    "current_year_reg": "24",
    "current_year_det": "18",
    "current_year_det_pct": "",
    "previous_year_reg": "60",
    "previous_year_det": "",
    "previous_year_det_pct": "16",
    "diff_reg_sign": "14",
    "diff_reg_value": "",
    "current_month_start": "02.01.2024",
    "current_month_end": "01.01.2024",
    "current_month": "2024-01",
    "previous_month_start": "01.02.2023",
    "previous_month_end": "29.02.2024",
    "current_year_start": "31.01.2024",
    "current_year_end": "02.29.2023",
    "previous_year_start": "",
    "previous_year_end": ""
  },
  {
    "pdf_file": "78.pdf",
    "sr_no": 7,
    "crime_head": "Snatching",
    "current_month_reg": "2",
    "current_month_det": "2",
    "previous_month_reg": "1",
    "previous_month_det": "1",
    "current_year_reg": "3",
    "current_year_det": "3",
    "current_year_det_pct": "",
    "previous_year_reg": "100",
    "previous_year_det": "",
    "previous_year_det_pct": "4",
    "diff_reg_sign": "4",
    "diff_reg_value": "",
    "current_month_start": "02.01.2024",
    "current_month_end": "01.01.2024",
    "current_month": "2024-01",
    "previous_month_start": "01.02.2023",
    "previous_month_end": "29.02.2024",
    "current_year_start": "31.01.2024",
    "current_year_end": "02.29.2023",
    "previous_year_start": "",
    "previous_year_end": ""
  },
  {
    "pdf_file": "78.pdf",
    "sr_no": 8,
    "crime_head": "Att.to.C.Robbery",
    "current_month_reg": "27",
    "current_month_det": "22",
    "previous_month_reg": "15",
    "previous_month_det": "9",
    "current_year_reg": "44",
    "current_year_det": "36",
    "current_year_det_pct": "",
    "previous_year_reg": "60",
    "previous_year_det": "",
    "previous_year_det_pct": "38",
    "diff_reg_sign": "25",
    "diff_reg_value": "",
    "current_month_start": "02.01.2024",
    "current_month_end": "01.01.2024",
    "current_month": "2024-01",
    "previous_month_start": "01.02.2023",
    "previous_month_end": "29.02.2024",
    "current_year_start": "31.01.2024",
    "current_year_end": "02.29.2023",
    "previous_year_start": "",
    "previous_year_end": ""
  },
  {
    "pdf_file": "78.pdf",
    "sr_no": 9,
    "crime_head": "Extortion",
    "current_month_reg": "24",
    "current_month_det": "12",
    "previous_month_reg": "22",
    "previous_month_det": "11",
    "current_year_reg": "46",
    "current_year_det": "26",
    "current_year_det_pct": "",
    "previous_year_reg": "50",
    "previous_year_det": "",
    "previous_year_det_pct": "38",
    "diff_reg_sign": "18",
    "diff_reg_value": "",
    "current_month_start": "02.01.2024",
    "current_month_end": "01.01.2024",
    "current_month": "2024-01",
    "previous_month_start": "01.02.2023",
    "previous_month_end": "29.02.2024",
    "current_year_start": "31.01.2024",
    "current_year_end": "02.29.2023",
    "previous_year_start": "",
    "previous_year_end": ""
  },
  {
    "pdf_file": "78.pdf",
    "sr_no": 10,
    "crime_head": "H.B.T.Day",
    "current_month_reg": "86",
    "current_month_det": "48",
    "previous_month_reg": "72",
    "previous_month_det": "37",
    "current_year_reg": "158",
    "current_year_det": "96",
    "current_year_det_pct": "",
    "previous_year_reg": "51",
    "previous_year_det": "",
    "previous_year_det_pct": "187",
    "diff_reg_sign": "97",
    "diff_reg_value": "",
    "current_month_start": "02.01.2024",
    "current_month_end": "01.01.2024",
    "current_month": "2024-01",
    "previous_month_start": "01.02.2023",
    "previous_month_end": "29.02.2024",
    "current_year_start": "31.01.2024",
    "current_year_end": "02.29.2023",
    "previous_year_start": "",
    "previous_year_end": ""
  },
  {
    "pdf_file": "78.pdf",
    "sr_no": 11,
    "crime_head": "H.B.T.Night.",
    "current_month_reg": "1,050",
    "current_month_det": "210",
    "previous_month_reg": "801",
    "previous_month_det": "207",
    "current_year_reg": "1,851",
    "current_year_det": "483",
    "current_year_det_pct": "",
    "previous_year_reg": "26",
    "previous_year_det": "",
    "previous_year_det_pct": "946",
    "diff_reg_sign": "317",
    "diff_reg_value": "",
    "current_month_start": "02.01.2024",
    "current_month_end": "01.01.2024",
    "current_month": "2024-01",
    "previous_month_start": "01.02.2023",
    "previous_month_end": "29.02.2024",
    "current_year_start": "31.01.2024",
    "current_year_end": "02.29.2023",
    "previous_year_start": "",
    "previous_year_end": ""
  },
  {
    "pdf_file": "78.pdf",
    "sr_no": 12,
    "crime_head": "Thefts.",
    "current_month_reg": "1",
    "current_month_det": "1",
    "previous_month_reg": "0",
    "previous_month_det": "0",
    "current_year_reg": "1",
    "current_year_det": "1",
    "current_year_det_pct": "",
    "previous_year_reg": "0",
    "previous_year_det": "",
    "previous_year_det_pct": "3",
    "diff_reg_sign": "2",
    "diff_reg_value": "",
    "current_month_start": "02.01.2024",
    "current_month_end": "01.01.2024",
    "current_month": "2024-01",
    "previous_month_start": "01.02.2023",
    "previous_month_end": "29.02.2024",
    "current_year_start": "31.01.2024",
    "current_year_end": "02.29.2023",
    "previous_year_start": "",
    "previous_year_end": ""
  },
  {
    "pdf_file": "78.pdf",
    "sr_no": 13,
    "crime_head": "Pocket Picking",
    "current_month_reg": "242",
    "current_month_det": "78",
    "previous_month_reg": "191",
    "previous_month_det": "51",
    "current_year_reg": "434",
    "current_year_det": "181",
    "current_year_det_pct": "",
    "previous_year_reg": "27",
    "previous_year_det": "",
    "previous_year_det_pct": "431",
    "diff_reg_sign": "191",
    "diff_reg_value": "",
    "current_month_start": "02.01.2024",
    "current_month_end": "01.01.2024",
    "current_month": "2024-01",
    "previous_month_start": "01.02.2023",
    "previous_month_end": "29.02.2024",
    "current_year_start": "31.01.2024",
    "current_year_end": "02.29.2023",
    "previous_year_start": "",
    "previous_year_end": ""
  },
  {
    "pdf_file": "78.pdf",
    "sr_no": 14,
    "crime_head": "M.V.Thefts.",
    "current_month_reg": "327",
    "current_month_det": "276",
    "previous_month_reg": "340",
    "previous_month_det": "285",
    "current_year_reg": "665",
    "current_year_det": "589",
    "current_year_det_pct": "",
    "previous_year_reg": "84",
    "previous_year_det": "",
    "previous_year_det_pct": "716",
    "diff_reg_sign": "560",
    "diff_reg_value": "",
    "current_month_start": "02.01.2024",
    "current_month_end": "01.01.2024",
    "current_month": "2024-01",
    "previous_month_start": "01.02.2023",
    "previous_month_end": "29.02.2024",
    "current_year_start": "31.01.2024",
    "current_year_end": "02.29.2023",
    "previous_year_start": "",
    "previous_year_end": ""
  },
  {
    "pdf_file": "78.pdf",
    "sr_no": 15,
    "crime_head": "Hurt",
    "current_month_reg": "16",
    "current_month_det": "15",
    "previous_month_reg": "28",
    "previous_month_det": "23",
    "current_year_reg": "43",
    "current_year_det": "39",
    "current_year_det_pct": "",
    "previous_year_reg": "82",
    "previous_year_det": "",
    "previous_year_det_pct": "51",
    "diff_reg_sign": "38",
    "diff_reg_value": "",
    "current_month_start": "02.01.2024",
    "current_month_end": "01.01.2024",
    "current_month": "2024-01",
    "previous_month_start": "01.02.2023",
    "previous_month_end": "29.02.2024",
    "current_year_start": "31.01.2024",
    "current_year_end": "02.29.2023",
    "previous_year_start": "",
    "previous_year_end": ""
  },
  {
    "pdf_file": "78.pdf",
    "sr_no": null,
    "crime_head": "Riots.",
    "current_month_reg": "",
    "current_month_det": "",
    "previous_month_reg": "",
    "previous_month_det": "",
    "current_year_reg": "",
    "current_year_det": "",
    "current_year_det_pct": "",
    "previous_year_reg": "",
    "previous_year_det": "",
    "previous_year_det_pct": "",
    "diff_reg_sign": "",
    "diff_reg_value": "",
    "current_month_start": "02.01.2024",
    "current_month_end": "01.01.2024",
    "current_month": "2024-01",
    "previous_month_start": "01.02.2023",
    "previous_month_end": "29.02.2024",
    "current_year_start": "31.01.2024",
    "current_year_end": "02.29.2023",
    "previous_year_start": "",
    "previous_year_end": ""
  },
  {
    "pdf_file": "78.pdf",
    "sr_no": 16,
    "crime_head": "Rape",
    "current_month_reg": "67",
    "current_month_det": "54",
    "previous_month_reg": "60",
    "previous_month_det": "47",
    "current_year_reg": "135",
    "current_year_det": "112",
    "current_year_det_pct": "",
    "previous_year_reg": "78",
    "previous_year_det": "",
    "previous_year_det_pct": "141",
    "diff_reg_sign": "116",
    "diff_reg_value": "",
    "current_month_start": "02.01.2024",
    "current_month_end": "01.01.2024",
    "current_month": "2024-01",
    "previous_month_start": "01.02.2023",
    "previous_month_end": "29.02.2024",
    "current_year_start": "31.01.2024",
    "current_year_end": "02.29.2023",
    "previous_year_start": "",
    "previous_year_end": ""
  },
  {
    "pdf_file": "78.pdf",
    "sr_no": 17,
    "crime_head": "Molestation",
    "current_month_reg": "168",
    "current_month_det": "140",
    "previous_month_reg": "184",
    "previous_month_det": "152",
    "current_year_reg": "353",
    "current_year_det": "310",
    "current_year_det_pct": "",
    "previous_year_reg": "83",
    "previous_year_det": "",
    "previous_year_det_pct": "346",
    "diff_reg_sign": "273",
    "diff_reg_value": "",
    "current_month_start": "02.01.2024",
    "current_month_end": "01.01.2024",
    "current_month": "2024-01",
    "previous_month_start": "01.02.2023",
    "previous_month_end": "29.02.2024",
    "current_year_start": "31.01.2024",
    "current_year_end": "02.29.2023",
    "previous_year_start": "",
    "previous_year_end": ""
  },
  {
    "pdf_file": "78.pdf",
    "sr_no": 18,
    "crime_head": "Other I.P.C.",
    "current_month_reg": "2,720",
    "current_month_det": "1,929",
    "previous_month_reg": "2,991",
    "previous_month_det": "2,289",
    "current_year_reg": "5,702",
    "current_year_det": "4,365",
    "current_year_det_pct": "",
    "previous_year_reg": "77",
    "previous_year_det": "",
    "previous_year_det_pct": "3,079",
    "diff_reg_sign": "1,627",
    "diff_reg_value": "",
    "current_month_start": "02.01.2024",
    "current_month_end": "01.01.2024",
    "current_month": "2024-01",
    "previous_month_start": "01.02.2023",
    "previous_month_end": "29.02.2024",
    "current_year_start": "31.01.2024",
    "current_year_end": "02.29.2023",
    "previous_year_start": "",
    "previous_year_end": ""
  },
  {
    "pdf_file": "78.pdf",
    "sr_no": null,
    "crime_head": "Total IPC",
    "current_month_reg": "4,833",
    "current_month_det": "2,876",
    "previous_month_reg": "4,805",
    "previous_month_det": "3,196",
    "current_year_reg": "9,639",
    "current_year_det": "6,429",
    "current_year_det_pct": "",
    "previous_year_reg": "67",
    "previous_year_det": "",
    "previous_year_det_pct": "6,175",
    "diff_reg_sign": "3,446",
    "diff_reg_value": "",
    "current_month_start": "02.01.2024",
    "current_month_end": "01.01.2024",
    "current_month": "2024-01",
    "previous_month_start": "01.02.2023",
    "previous_month_end": "29.02.2024",
    "current_year_start": "31.01.2024",
    "current_year_end": "02.29.2023",
    "previous_year_start": "",
    "previous_year_end": ""
  }
]